{
"type": "FeatureCollection",
"name": "covid19-cluster",
"crs": { "type": "name", "properties": { "name": "urn:ogc:def:crs:OGC:1.3:CRS84" } },
"features": [
{ "type": "Feature", "properties": { "num": 0 }, "geometry": { "type": "Point", "coordinates": [ 141.312318366788872, 43.054778510066484 ] } },
{ "type": "Feature", "properties": { "num": 0 }, "geometry": { "type": "Point", "coordinates": [ 143.854546520717747, 43.796208173748553 ] } },
{ "type": "Feature", "properties": { "num": 0 }, "geometry": { "type": "Point", "coordinates": [ 139.010300747089502, 37.920829451817866 ] } },
{ "type": "Feature", "properties": { "num": 0 }, "geometry": { "type": "Point", "coordinates": [ 139.352082, 35.564372 ] } },
{ "type": "Feature", "properties": { "num": 0 }, "geometry": { "type": "Point", "coordinates": [ 139.793487176400276, 35.664891863828288 ] } },
{ "type": "Feature", "properties": { "num": 0 }, "geometry": { "type": "Point", "coordinates": [ 139.93110779496925, 35.701475390743816 ] } },
{ "type": "Feature", "properties": { "num": 0 }, "geometry": { "type": "Point", "coordinates": [ 139.793487176400276, 35.689282745653216 ] } },
{ "type": "Feature", "properties": { "num": 0 }, "geometry": { "type": "Point", "coordinates": [ 136.89344541419203, 35.200051376464522 ] } },
{ "type": "Feature", "properties": { "num": 0 }, "geometry": { "type": "Point", "coordinates": [ 136.803366463855951, 35.085470139349283 ] } },
{ "type": "Feature", "properties": { "num": 0 }, "geometry": null },
{ "type": "Feature", "properties": { "num": 0 }, "geometry": { "type": "Point", "coordinates": [ 135.422155892036358, 34.687283096251178 ] } },
{ "type": "Feature", "properties": { "num": 0 }, "geometry": { "type": "Point", "coordinates": [ 135.394631768322569, 34.773652105459561 ] } },
{ "type": "Feature", "properties": { "num": 0 }, "geometry": { "type": "Point", "coordinates": [ 135.226984832974864, 34.703741293613504 ] } },
{ "type": "Feature", "properties": { "num": 0 }, "geometry": { "type": "Point", "coordinates": [ 134.660754200000014, 34.8106742 ] } },
{ "type": "Feature", "properties": { "num": 0 }, "geometry": { "type": "Point", "coordinates": [ 131.583791730494141, 33.247158138300897 ] } },
{ "type": "Feature", "properties": { "num": 0 }, "geometry": { "type": "Point", "coordinates": [ 135.064342283757014, 34.629653637994188 ] } },
{ "type": "Feature", "properties": { "num": 0 }, "geometry": { "type": "Point", "coordinates": [ 135.762454148861508, 35.00967623492749 ] } },
{ "type": "Feature", "properties": { "num": 0 }, "geometry": { "type": "Point", "coordinates": [ 137.05859015647485, 35.422612506989168 ] } },
{ "type": "Feature", "properties": { "num": 0 }, "geometry": { "type": "Point", "coordinates": [ 139.415656023601798, 35.512280064043843 ] } },
{ "type": "Feature", "properties": { "num": 0 }, "geometry": { "type": "Point", "coordinates": [ 139.380625320693326, 36.278473977775121 ] } },
{ "type": "Feature", "properties": { "num": 0 }, "geometry": { "type": "Point", "coordinates": [ 139.53576129071655, 36.234084185470742 ] } },
{ "type": "Feature", "properties": { "num": 0 }, "geometry": { "type": "Point", "coordinates": [ 139.645857785571735, 35.683185724102295 ] } },
{ "type": "Feature", "properties": { "num": 0 }, "geometry": { "type": "Point", "coordinates": [ 139.720923577518448, 35.699443412682449 ] } },
{ "type": "Feature", "properties": { "num": 0 }, "geometry": { "type": "Point", "coordinates": [ 140.04370648288932, 35.898330944653232 ] } },
{ "type": "Feature", "properties": { "num": 0 }, "geometry": { "type": "Point", "coordinates": [ 140.068728413538224, 36.072454285503703 ] } },
{ "type": "Feature", "properties": { "num": 0 }, "geometry": { "type": "Point", "coordinates": [ 140.666752556047129, 35.823299264693176 ] } },
{ "type": "Feature", "properties": { "num": 0 }, "geometry": { "type": "Point", "coordinates": [ 140.851914842848998, 38.258570322689692 ] } }
]
}
